stock_price_simulator/__init__.py
stock_price_simulator/candle.py
stock_price_simulator/history.py
stock_price_simulator-0.0.6.dist-info/METADATA
stock_price_simulator-0.0.6.dist-info/WHEEL
stock_price_simulator-0.0.6.dist-info/licenses/LICENSE
stock_price_simulator-0.0.6.dist-info/RECORD
