Metadata-Version: 2.1
Name: stock_price_simulator
Version: 0.0.6
Summary: A stock price simulator
Project-URL: Github, https://github.com/Cereal38/stock_price_simulator
Author-email: Cereal38 <guillaume.bruncosmegazot@gmail.com>
License-File: LICENSE
Classifier: License :: OSI Approved :: MIT License
Classifier: Operating System :: OS Independent
Classifier: Programming Language :: Python :: 3
Requires-Python: >=3.7
Requires-Dist: mplfinance>=0.12.9b7
Requires-Dist: pandas>=2.0.3
